[
    {
        "gene":"MOV10",
        "degreeCentrality":0.02158273381294964
    },
    {
        "gene":"PRKAG3",
        "degreeCentrality":0.014388489208633094
    },
    {
        "gene":"ZFPM1",
        "degreeCentrality":0.007194244604316547
    },
    {
        "gene":"AKT1",
        "degreeCentrality":0.007194244604316547
    },
    {
        "gene":"ATRIP",
        "degreeCentrality":0.007194244604316547
    },
    {
        "gene":"ARL2BP",
        "degreeCentrality":0.007194244604316547
    },
    {
        "gene":"POLR3K",
        "degreeCentrality":0.007194244604316547
    },
    {
        "gene":"KIF2C",
        "degreeCentrality":0.03597122302158273
    },
    {
        "gene":"ZNF143",
        "degreeCentrality":0.007194244604316547
    },
    {
        "gene":"CD180",
        "degreeCentrality":0.007194244604316547
    },
    {
        "gene":"GATM",
        "degreeCentrality":0.014388489208633094
    },
    {
        "gene":"PIK3CA",
        "degreeCentrality":0.007194244604316547
    },
    {
        "gene":"PIK3CB",
        "degreeCentrality":0.05035971223021583
    },
    {
        "gene":"MAP3K1",
        "degreeCentrality":0.007194244604316547
    },
    {
        "gene":"PIK3CG",
        "degreeCentrality":0.007194244604316547
    },
    {
        "gene":"CDKN2A",
        "degreeCentrality":0.007194244604316547
    },
    {
        "gene":"BDP1",
        "degreeCentrality":0.007194244604316547
    },
    {
        "gene":"MT-ATP6",
        "degreeCentrality":0.007194244604316547
    },
    {
        "gene":"MAPRE1",
        "degreeCentrality":0.007194244604316547
    },
    {
        "gene":"PSMF1",
        "degreeCentrality":0.007194244604316547
    },
    {
        "gene":"BRCA1",
        "degreeCentrality":0.014388489208633094
    },
    {
        "gene":"CDKN2C",
        "degreeCentrality":0.007194244604316547
    },
    {
        "gene":"STK11",
        "degreeCentrality":0.007194244604316547
    },
    {
        "gene":"ERBB4",
        "degreeCentrality":0.007194244604316547
    },
    {
        "gene":"AQP1",
        "degreeCentrality":0.007194244604316547
    },
    {
        "gene":"IDH2",
        "degreeCentrality":0.007194244604316547
    },
    {
        "gene":"IDH1",
        "degreeCentrality":0.007194244604316547
    },
    {
        "gene":"HLA-DRB1",
        "degreeCentrality":0.007194244604316547
    },
    {
        "gene":"FGFR3",
        "degreeCentrality":0.007194244604316547
    },
    {
        "gene":"SNAPC4",
        "degreeCentrality":0.007194244604316547
    },
    {
        "gene":"CENPW",
        "degreeCentrality":0.007194244604316547
    },
    {
        "gene":"FGFR2",
        "degreeCentrality":0.007194244604316547
    },
    {
        "gene":"GATA3",
        "degreeCentrality":0.007194244604316547
    },
    {
        "gene":"KRAS",
        "degreeCentrality":0.007194244604316547
    },
    {
        "gene":"FOXA2",
        "degreeCentrality":0.007194244604316547
    },
    {
        "gene":"CCND1",
        "degreeCentrality":0.007194244604316547
    },
    {
        "gene":"PTPN11",
        "degreeCentrality":0.007194244604316547
    },
    {
        "gene":"RBBP5",
        "degreeCentrality":0.007194244604316547
    },
    {
        "gene":"KIT",
        "degreeCentrality":0.007194244604316547
    },
    {
        "gene":"PTEN",
        "degreeCentrality":0.007194244604316547
    },
    {
        "gene":"RUNX1",
        "degreeCentrality":0.007194244604316547
    },
    {
        "gene":"TLR4",
        "degreeCentrality":0.007194244604316547
    },
    {
        "gene":"RBX1",
        "degreeCentrality":0.007194244604316547
    },
    {
        "gene":"SIN3A",
        "degreeCentrality":0.007194244604316547
    },
    {
        "gene":"ACVR1B",
        "degreeCentrality":0.007194244604316547
    },
    {
        "gene":"CDKN1B",
        "degreeCentrality":0.007194244604316547
    },
    {
        "gene":"CDKN1A",
        "degreeCentrality":0.007194244604316547
    },
    {
        "gene":"RPS27A",
        "degreeCentrality":0.007194244604316547
    },
    {
        "gene":"HIF1A",
        "degreeCentrality":0.007194244604316547
    },
    {
        "gene":"EIF5B",
        "degreeCentrality":0.02158273381294964
    },
    {
        "gene":"APOA1",
        "degreeCentrality":0.014388489208633094
    },
    {
        "gene":"U2AF1",
        "degreeCentrality":0.007194244604316547
    },
    {
        "gene":"SOX17",
        "degreeCentrality":0.007194244604316547
    },
    {
        "gene":"TIAM1",
        "degreeCentrality":0.007194244604316547
    },
    {
        "gene":"GRB2",
        "degreeCentrality":0.05035971223021583
    },
    {
        "gene":"ADIPOQ",
        "degreeCentrality":0.007194244604316547
    },
    {
        "gene":"PIK3R1",
        "degreeCentrality":0.007194244604316547
    },
    {
        "gene":"PCBP1",
        "degreeCentrality":0.007194244604316547
    },
    {
        "gene":"B4GALT3",
        "degreeCentrality":0.007194244604316547
    },
    {
        "gene":"CHEK2",
        "degreeCentrality":0.007194244604316547
    },
    {
        "gene":"SMC1A",
        "degreeCentrality":0.007194244604316547
    },
    {
        "gene":"EPHB6",
        "degreeCentrality":0.007194244604316547
    },
    {
        "gene":"STAG2",
        "degreeCentrality":0.007194244604316547
    },
    {
        "gene":"PARP1",
        "degreeCentrality":0.007194244604316547
    },
    {
        "gene":"HIST1H2BD",
        "degreeCentrality":0.007194244604316547
    },
    {
        "gene":"ANAPC5",
        "degreeCentrality":0.014388489208633094
    },
    {
        "gene":"POLR2J",
        "degreeCentrality":0.04316546762589928
    },
    {
        "gene":"TAF4",
        "degreeCentrality":0.007194244604316547
    },
    {
        "gene":"TP53",
        "degreeCentrality":0.007194244604316547
    },
    {
        "gene":"PALB2",
        "degreeCentrality":0.007194244604316547
    },
    {
        "gene":"B3GNT3",
        "degreeCentrality":0.007194244604316547
    },
    {
        "gene":"SLC22A4",
        "degreeCentrality":0.007194244604316547
    },
    {
        "gene":"BTC",
        "degreeCentrality":0.007194244604316547
    },
    {
        "gene":"PDX1",
        "degreeCentrality":0.007194244604316547
    },
    {
        "gene":"PHF2",
        "degreeCentrality":0.007194244604316547
    },
    {
        "gene":"LAMTOR3",
        "degreeCentrality":0.007194244604316547
    },
    {
        "gene":"EFNB3",
        "degreeCentrality":0.014388489208633094
    },
    {
        "gene":"PDGFRA",
        "degreeCentrality":0.007194244604316547
    },
    {
        "gene":"SMAD9",
        "degreeCentrality":0.007194244604316547
    },
    {
        "gene":"POLQ",
        "degreeCentrality":0.007194244604316547
    },
    {
        "gene":"SMAD4",
        "degreeCentrality":0.007194244604316547
    },
    {
        "gene":"EPHA3",
        "degreeCentrality":0.007194244604316547
    },
    {
        "gene":"SMAD2",
        "degreeCentrality":0.007194244604316547
    },
    {
        "gene":"MAPK10",
        "degreeCentrality":0.007194244604316547
    },
    {
        "gene":"CTNND1",
        "degreeCentrality":0.007194244604316547
    },
    {
        "gene":"SOX9",
        "degreeCentrality":0.007194244604316547
    },
    {
        "gene":"NCOR1",
        "degreeCentrality":0.007194244604316547
    },
    {
        "gene":"CGN",
        "degreeCentrality":0.007194244604316547
    },
    {
        "gene":"SMC3",
        "degreeCentrality":0.007194244604316547
    },
    {
        "gene":"FANCG",
        "degreeCentrality":0.007194244604316547
    },
    {
        "gene":"BRAF",
        "degreeCentrality":0.007194244604316547
    },
    {
        "gene":"FBXW7",
        "degreeCentrality":0.007194244604316547
    },
    {
        "gene":"TGFBR2",
        "degreeCentrality":0.007194244604316547
    },
    {
        "gene":"KISS1",
        "degreeCentrality":0.007194244604316547
    },
    {
        "gene":"RPL5",
        "degreeCentrality":0.007194244604316547
    },
    {
        "gene":"RIF1",
        "degreeCentrality":0.007194244604316547
    },
    {
        "gene":"RBL2",
        "degreeCentrality":0.007194244604316547
    },
    {
        "gene":"EGFR",
        "degreeCentrality":0.007194244604316547
    },
    {
        "gene":"TET2",
        "degreeCentrality":0.007194244604316547
    },
    {
        "gene":"LEF1",
        "degreeCentrality":0.007194244604316547
    },
    {
        "gene":"EP300",
        "degreeCentrality":0.007194244604316547
    },
    {
        "gene":"TBL1XR1",
        "degreeCentrality":0.007194244604316547
    },
    {
        "gene":"ARID5B",
        "degreeCentrality":0.007194244604316547
    },
    {
        "gene":"TDG",
        "degreeCentrality":0.007194244604316547
    },
    {
        "gene":"TAF1L",
        "degreeCentrality":0.007194244604316547
    },
    {
        "gene":"KEAP1",
        "degreeCentrality":0.007194244604316547
    },
    {
        "gene":"EZH2",
        "degreeCentrality":0.007194244604316547
    },
    {
        "gene":"CDK4",
        "degreeCentrality":0.007194244604316547
    },
    {
        "gene":"CDK8",
        "degreeCentrality":0.007194244604316547
    },
    {
        "gene":"RNF146",
        "degreeCentrality":0.007194244604316547
    },
    {
        "gene":"PPP2R1A",
        "degreeCentrality":0.007194244604316547
    },
    {
        "gene":"CDH17",
        "degreeCentrality":0.007194244604316547
    },
    {
        "gene":"ACVR2A",
        "degreeCentrality":0.007194244604316547
    },
    {
        "gene":"ERCC2",
        "degreeCentrality":0.007194244604316547
    },
    {
        "gene":"JARID2",
        "degreeCentrality":0.007194244604316547
    },
    {
        "gene":"ERCC6",
        "degreeCentrality":0.007194244604316547
    },
    {
        "gene":"CTNNB1",
        "degreeCentrality":0.014388489208633094
    },
    {
        "gene":"VHL",
        "degreeCentrality":0.007194244604316547
    },
    {
        "gene":"USP9X",
        "degreeCentrality":0.007194244604316547
    },
    {
        "gene":"BRCA2",
        "degreeCentrality":0.007194244604316547
    },
    {
        "gene":"TDGF1",
        "degreeCentrality":0.007194244604316547
    },
    {
        "gene":"MAP2K4",
        "degreeCentrality":0.007194244604316547
    },
    {
        "gene":"CEBPA",
        "degreeCentrality":0.007194244604316547
    },
    {
        "gene":"AXIN2",
        "degreeCentrality":0.007194244604316547
    },
    {
        "gene":"NRAS",
        "degreeCentrality":0.007194244604316547
    },
    {
        "gene":"RPL22",
        "degreeCentrality":0.007194244604316547
    },
    {
        "gene":"AJUBA",
        "degreeCentrality":0.007194244604316547
    },
    {
        "gene":"YWHAE",
        "degreeCentrality":0.007194244604316547
    },
    {
        "gene":"DNMT3A",
        "degreeCentrality":0.014388489208633094
    },
    {
        "gene":"RAD21",
        "degreeCentrality":0.007194244604316547
    },
    {
        "gene":"SPOP",
        "degreeCentrality":0.007194244604316547
    },
    {
        "gene":"SF3B1",
        "degreeCentrality":0.007194244604316547
    },
    {
        "gene":"HGF",
        "degreeCentrality":0.014388489208633094
    },
    {
        "gene":"NPM1",
        "degreeCentrality":0.007194244604316547
    },
    {
        "gene":"PHYH",
        "degreeCentrality":0.007194244604316547
    },
    {
        "gene":"NOTCH1",
        "degreeCentrality":0.007194244604316547
    },
    {
        "gene":"CHD9",
        "degreeCentrality":0.007194244604316547
    },
    {
        "gene":"ARHGAP35",
        "degreeCentrality":0.007194244604316547
    },
    {
        "gene":"EIF4A2",
        "degreeCentrality":0.007194244604316547
    },
    {
        "gene":"ATF2",
        "degreeCentrality":0.007194244604316547
    }
]